{
  "timestamp": "2026-04-03T07:45:03.062Z",
  "count": 42,
  "byType": {
    "general": 32,
    "bug_report": 1,
    "crash_report": 1,
    "github": 7,
    "diagnostic": 1
  },
  "newFingerprints": [],
  "deepResearch": {
    "researched": 0,
    "added": 0,
    "details": []
  },
  "diagnostics": [
    {
      "id": "imap_498982",
      "type": "general",
      "subj": "[com.dlnraja.tuya.zigbee] Build #2014 has been created",
      "from": "homey_system",
      "date": "2026-03-04T23:45:21.000Z",
      "pseudo": {
        "source": "homey_system",
        "username": null
      },
      "fps": {
        "mfr": [],
        "pid": []
      },
      "errs": [],
      "devices": [],
      "xref": [],
      "ghInfo": null,
      "forumInfo": null,
      "crashInfo": null,
      "ai": null,
      "homeyVersion": null,
      "appVersion": null,
      "bodyLength": 508,
      "contentType": "text/html->text"
    },
    {
      "id": "imap_498983",
      "type": "general",
      "subj": "[com.dlnraja.tuya.zigbee] Your build is now draft",
      "from": "homey_system",
      "date": "2026-03-04T23:45:33.000Z",
      "pseudo": {
        "source": "homey_system",
        "username": null
      },
      "fps": {
        "mfr": [],
        "pid": []
      },
      "errs": [],
      "devices": [],
      "xref": [],
      "ghInfo": null,
      "forumInfo": null,
      "crashInfo": null,
      "ai": null,
      "homeyVersion": null,
      "appVersion": null,
      "bodyLength": 564,
      "contentType": "text/html->text"
    },
    {
      "id": "imap_498984",
      "type": "general",
      "subj": "[com.dlnraja.tuya.zigbee] Build #2015 has been created",
      "from": "homey_system",
      "date": "2026-03-05T00:12:52.000Z",
      "pseudo": {
        "source": "homey_system",
        "username": null
      },
      "fps": {
        "mfr": [],
        "pid": []
      },
      "errs": [],
      "devices": [],
      "xref": [],
      "ghInfo": null,
      "forumInfo": null,
      "crashInfo": null,
      "ai": null,
      "homeyVersion": null,
      "appVersion": null,
      "bodyLength": 508,
      "contentType": "text/html->text"
    },
    {
      "id": "imap_498985",
      "type": "general",
      "subj": "[com.dlnraja.tuya.zigbee] Your build is now draft",
      "from": "homey_system",
      "date": "2026-03-05T00:13:04.000Z",
      "pseudo": {
        "source": "homey_system",
        "username": null
      },
      "fps": {
        "mfr": [],
        "pid": []
      },
      "errs": [],
      "devices": [],
      "xref": [],
      "ghInfo": null,
      "forumInfo": null,
      "crashInfo": null,
      "ai": null,
      "homeyVersion": null,
      "appVersion": null,
      "bodyLength": 564,
      "contentType": "text/html->text"
    },
    {
      "id": "imap_498986",
      "type": "general",
      "subj": "[com.dlnraja.tuya.zigbee] Build #2016 has been created",
      "from": "homey_system",
      "date": "2026-03-05T00:28:37.000Z",
      "pseudo": {
        "source": "homey_system",
        "username": null
      },
      "fps": {
        "mfr": [],
        "pid": []
      },
      "errs": [],
      "devices": [],
      "xref": [],
      "ghInfo": null,
      "forumInfo": null,
      "crashInfo": null,
      "ai": null,
      "homeyVersion": null,
      "appVersion": null,
      "bodyLength": 508,
      "contentType": "text/html->text"
    },
    {
      "id": "imap_498987",
      "type": "general",
      "subj": "[com.dlnraja.tuya.zigbee] Your build is now draft",
      "from": "homey_system",
      "date": "2026-03-05T00:28:49.000Z",
      "pseudo": {
        "source": "homey_system",
        "username": null
      },
      "fps": {
        "mfr": [],
        "pid": []
      },
      "errs": [],
      "devices": [],
      "xref": [],
      "ghInfo": null,
      "forumInfo": null,
      "crashInfo": null,
      "ai": null,
      "homeyVersion": null,
      "appVersion": null,
      "bodyLength": 564,
      "contentType": "text/html->text"
    },
    {
      "id": "imap_498988",
      "type": "general",
      "subj": "[com.dlnraja.tuya.zigbee] Build #2017 has been created",
      "from": "homey_system",
      "date": "2026-03-05T01:05:05.000Z",
      "pseudo": {
        "source": "homey_system",
        "username": null
      },
      "fps": {
        "mfr": [],
        "pid": []
      },
      "errs": [],
      "devices": [],
      "xref": [],
      "ghInfo": null,
      "forumInfo": null,
      "crashInfo": null,
      "ai": null,
      "homeyVersion": null,
      "appVersion": null,
      "bodyLength": 508,
      "contentType": "text/html->text"
    },
    {
      "id": "imap_498989",
      "type": "general",
      "subj": "[com.dlnraja.tuya.zigbee] Your build is now draft",
      "from": "homey_system",
      "date": "2026-03-05T01:05:19.000Z",
      "pseudo": {
        "source": "homey_system",
        "username": null
      },
      "fps": {
        "mfr": [],
        "pid": []
      },
      "errs": [],
      "devices": [],
      "xref": [],
      "ghInfo": null,
      "forumInfo": null,
      "crashInfo": null,
      "ai": null,
      "homeyVersion": null,
      "appVersion": null,
      "bodyLength": 564,
      "contentType": "text/html->text"
    },
    {
      "id": "imap_498990",
      "type": "general",
      "subj": "[com.dlnraja.tuya.zigbee] Build #2018 has been created",
      "from": "homey_system",
      "date": "2026-03-05T01:15:56.000Z",
      "pseudo": {
        "source": "homey_system",
        "username": null
      },
      "fps": {
        "mfr": [],
        "pid": []
      },
      "errs": [],
      "devices": [],
      "xref": [],
      "ghInfo": null,
      "forumInfo": null,
      "crashInfo": null,
      "ai": null,
      "homeyVersion": null,
      "appVersion": null,
      "bodyLength": 508,
      "contentType": "text/html->text"
    },
    {
      "id": "imap_498991",
      "type": "general",
      "subj": "[com.dlnraja.tuya.zigbee] Your build is now draft",
      "from": "homey_system",
      "date": "2026-03-05T01:16:11.000Z",
      "pseudo": {
        "source": "homey_system",
        "username": null
      },
      "fps": {
        "mfr": [],
        "pid": []
      },
      "errs": [],
      "devices": [],
      "xref": [],
      "ghInfo": null,
      "forumInfo": null,
      "crashInfo": null,
      "ai": null,
      "homeyVersion": null,
      "appVersion": null,
      "bodyLength": 564,
      "contentType": "text/html->text"
    },
    {
      "id": "imap_498996",
      "type": "general",
      "subj": "[com.dlnraja.tuya.zigbee] Build #2019 has been created",
      "from": "homey_system",
      "date": "2026-03-05T02:55:39.000Z",
      "pseudo": {
        "source": "homey_system",
        "username": null
      },
      "fps": {
        "mfr": [],
        "pid": []
      },
      "errs": [],
      "devices": [],
      "xref": [],
      "ghInfo": null,
      "forumInfo": null,
      "crashInfo": null,
      "ai": null,
      "homeyVersion": null,
      "appVersion": null,
      "bodyLength": 508,
      "contentType": "text/html->text"
    },
    {
      "id": "imap_498997",
      "type": "general",
      "subj": "[com.dlnraja.tuya.zigbee] Your build is now draft",
      "from": "homey_system",
      "date": "2026-03-05T02:55:51.000Z",
      "pseudo": {
        "source": "homey_system",
        "username": null
      },
      "fps": {
        "mfr": [],
        "pid": []
      },
      "errs": [],
      "devices": [],
      "xref": [],
      "ghInfo": null,
      "forumInfo": null,
      "crashInfo": null,
      "ai": null,
      "homeyVersion": null,
      "appVersion": null,
      "bodyLength": 564,
      "contentType": "text/html->text"
    },
    {
      "id": "imap_498998",
      "type": "general",
      "subj": "[com.dlnraja.tuya.zigbee] Build #2020 has been created",
      "from": "homey_system",
      "date": "2026-03-05T03:03:29.000Z",
      "pseudo": {
        "source": "homey_system",
        "username": null
      },
      "fps": {
        "mfr": [],
        "pid": []
      },
      "errs": [],
      "devices": [],
      "xref": [],
      "ghInfo": null,
      "forumInfo": null,
      "crashInfo": null,
      "ai": null,
      "homeyVersion": null,
      "appVersion": null,
      "bodyLength": 508,
      "contentType": "text/html->text"
    },
    {
      "id": "imap_498999",
      "type": "general",
      "subj": "[com.dlnraja.tuya.zigbee] Your build is now draft",
      "from": "homey_system",
      "date": "2026-03-05T03:03:42.000Z",
      "pseudo": {
        "source": "homey_system",
        "username": null
      },
      "fps": {
        "mfr": [],
        "pid": []
      },
      "errs": [],
      "devices": [],
      "xref": [],
      "ghInfo": null,
      "forumInfo": null,
      "crashInfo": null,
      "ai": null,
      "homeyVersion": null,
      "appVersion": null,
      "bodyLength": 564,
      "contentType": "text/html->text"
    },
    {
      "id": "imap_499000",
      "type": "general",
      "subj": "[com.dlnraja.tuya.zigbee] Build #2021 has been created",
      "from": "homey_system",
      "date": "2026-03-05T03:25:46.000Z",
      "pseudo": {
        "source": "homey_system",
        "username": null
      },
      "fps": {
        "mfr": [],
        "pid": []
      },
      "errs": [],
      "devices": [],
      "xref": [],
      "ghInfo": null,
      "forumInfo": null,
      "crashInfo": null,
      "ai": null,
      "homeyVersion": null,
      "appVersion": null,
      "bodyLength": 508,
      "contentType": "text/html->text"
    },
    {
      "id": "imap_499001",
      "type": "general",
      "subj": "[com.dlnraja.tuya.zigbee] Your build is now draft",
      "from": "homey_system",
      "date": "2026-03-05T03:25:58.000Z",
      "pseudo": {
        "source": "homey_system",
        "username": null
      },
      "fps": {
        "mfr": [],
        "pid": []
      },
      "errs": [],
      "devices": [],
      "xref": [],
      "ghInfo": null,
      "forumInfo": null,
      "crashInfo": null,
      "ai": null,
      "homeyVersion": null,
      "appVersion": null,
      "bodyLength": 564,
      "contentType": "text/html->text"
    },
    {
      "id": "imap_499002",
      "type": "general",
      "subj": "[com.dlnraja.tuya.zigbee] Build #2022 has been created",
      "from": "homey_system",
      "date": "2026-03-05T03:59:32.000Z",
      "pseudo": {
        "source": "homey_system",
        "username": null
      },
      "fps": {
        "mfr": [],
        "pid": []
      },
      "errs": [],
      "devices": [],
      "xref": [],
      "ghInfo": null,
      "forumInfo": null,
      "crashInfo": null,
      "ai": null,
      "homeyVersion": null,
      "appVersion": null,
      "bodyLength": 508,
      "contentType": "text/html->text"
    },
    {
      "id": "imap_499003",
      "type": "general",
      "subj": "[com.dlnraja.tuya.zigbee] Your build is now draft",
      "from": "homey_system",
      "date": "2026-03-05T03:59:45.000Z",
      "pseudo": {
        "source": "homey_system",
        "username": null
      },
      "fps": {
        "mfr": [],
        "pid": []
      },
      "errs": [],
      "devices": [],
      "xref": [],
      "ghInfo": null,
      "forumInfo": null,
      "crashInfo": null,
      "ai": null,
      "homeyVersion": null,
      "appVersion": null,
      "bodyLength": 564,
      "contentType": "text/html->text"
    },
    {
      "id": "imap_499005",
      "type": "general",
      "subj": "[com.dlnraja.tuya.zigbee] Build #2022 is now testing",
      "from": "homey_system",
      "date": "2026-03-05T04:14:48.000Z",
      "pseudo": {
        "source": "homey_system",
        "username": null
      },
      "fps": {
        "mfr": [],
        "pid": []
      },
      "errs": [],
      "devices": [],
      "xref": [],
      "ghInfo": null,
      "forumInfo": null,
      "crashInfo": null,
      "ai": null,
      "homeyVersion": null,
      "appVersion": null,
      "bodyLength": 559,
      "contentType": "text/html->text"
    },
    {
      "id": "imap_499006",
      "type": "general",
      "subj": "[com.dlnraja.tuya.zigbee] Build #2023 has been created",
      "from": "homey_system",
      "date": "2026-03-05T04:17:12.000Z",
      "pseudo": {
        "source": "homey_system",
        "username": null
      },
      "fps": {
        "mfr": [],
        "pid": []
      },
      "errs": [],
      "devices": [],
      "xref": [],
      "ghInfo": null,
      "forumInfo": null,
      "crashInfo": null,
      "ai": null,
      "homeyVersion": null,
      "appVersion": null,
      "bodyLength": 508,
      "contentType": "text/html->text"
    },
    {
      "id": "imap_499007",
      "type": "general",
      "subj": "[com.dlnraja.tuya.zigbee] Your build is now draft",
      "from": "homey_system",
      "date": "2026-03-05T04:17:24.000Z",
      "pseudo": {
        "source": "homey_system",
        "username": null
      },
      "fps": {
        "mfr": [],
        "pid": []
      },
      "errs": [],
      "devices": [],
      "xref": [],
      "ghInfo": null,
      "forumInfo": null,
      "crashInfo": null,
      "ai": null,
      "homeyVersion": null,
      "appVersion": null,
      "bodyLength": 564,
      "contentType": "text/html->text"
    },
    {
      "id": "imap_499008",
      "type": "general",
      "subj": "[com.dlnraja.tuya.zigbee] Build #2023 is now testing",
      "from": "homey_system",
      "date": "2026-03-05T04:20:10.000Z",
      "pseudo": {
        "source": "homey_system",
        "username": null
      },
      "fps": {
        "mfr": [],
        "pid": []
      },
      "errs": [],
      "devices": [],
      "xref": [],
      "ghInfo": null,
      "forumInfo": null,
      "crashInfo": null,
      "ai": null,
      "homeyVersion": null,
      "appVersion": null,
      "bodyLength": 559,
      "contentType": "text/html->text"
    },
    {
      "id": "imap_499009",
      "type": "general",
      "subj": "[com.dlnraja.tuya.zigbee] Build #2021 is now testing",
      "from": "homey_system",
      "date": "2026-03-05T04:24:28.000Z",
      "pseudo": {
        "source": "homey_system",
        "username": null
      },
      "fps": {
        "mfr": [],
        "pid": []
      },
      "errs": [],
      "devices": [],
      "xref": [],
      "ghInfo": null,
      "forumInfo": null,
      "crashInfo": null,
      "ai": null,
      "homeyVersion": null,
      "appVersion": null,
      "bodyLength": 559,
      "contentType": "text/html->text"
    },
    {
      "id": "imap_499011",
      "type": "general",
      "subj": "[com.dlnraja.tuya.zigbee] Build #2024 has been created",
      "from": "homey_system",
      "date": "2026-03-05T04:33:37.000Z",
      "pseudo": {
        "source": "homey_system",
        "username": null
      },
      "fps": {
        "mfr": [],
        "pid": []
      },
      "errs": [],
      "devices": [],
      "xref": [],
      "ghInfo": null,
      "forumInfo": null,
      "crashInfo": null,
      "ai": null,
      "homeyVersion": null,
      "appVersion": null,
      "bodyLength": 508,
      "contentType": "text/html->text"
    },
    {
      "id": "imap_499012",
      "type": "general",
      "subj": "[com.dlnraja.tuya.zigbee] Your build is now draft",
      "from": "homey_system",
      "date": "2026-03-05T04:33:50.000Z",
      "pseudo": {
        "source": "homey_system",
        "username": null
      },
      "fps": {
        "mfr": [],
        "pid": []
      },
      "errs": [],
      "devices": [],
      "xref": [],
      "ghInfo": null,
      "forumInfo": null,
      "crashInfo": null,
      "ai": null,
      "homeyVersion": null,
      "appVersion": null,
      "bodyLength": 564,
      "contentType": "text/html->text"
    },
    {
      "id": "imap_499013",
      "type": "general",
      "subj": "[com.dlnraja.tuya.zigbee] Build #2024 is now testing",
      "from": "homey_system",
      "date": "2026-03-05T04:38:51.000Z",
      "pseudo": {
        "source": "homey_system",
        "username": null
      },
      "fps": {
        "mfr": [],
        "pid": []
      },
      "errs": [],
      "devices": [],
      "xref": [],
      "ghInfo": null,
      "forumInfo": null,
      "crashInfo": null,
      "ai": null,
      "homeyVersion": null,
      "appVersion": null,
      "bodyLength": 559,
      "contentType": "text/html->text"
    },
    {
      "id": "imap_499014",
      "type": "general",
      "subj": "[com.dlnraja.tuya.zigbee] Build #2020 is now testing",
      "from": "homey_system",
      "date": "2026-03-05T04:40:36.000Z",
      "pseudo": {
        "source": "homey_system",
        "username": null
      },
      "fps": {
        "mfr": [],
        "pid": []
      },
      "errs": [],
      "devices": [],
      "xref": [],
      "ghInfo": null,
      "forumInfo": null,
      "crashInfo": null,
      "ai": null,
      "homeyVersion": null,
      "appVersion": null,
      "bodyLength": 559,
      "contentType": "text/html->text"
    },
    {
      "id": "imap_499035",
      "type": "general",
      "subj": "Frontier Alliance: From Experimentation  to Enterprise",
      "from": "user",
      "date": "2026-03-05T07:02:55.000Z",
      "pseudo": {
        "source": "user",
        "username": "B.L."
      },
      "fps": {
        "mfr": [],
        "pid": []
      },
      "errs": [],
      "devices": [],
      "xref": [],
      "ghInfo": null,
      "forumInfo": null,
      "crashInfo": null,
      "ai": null,
      "homeyVersion": null,
      "appVersion": null,
      "bodyLength": 9566,
      "contentType": "text/plain"
    },
    {
      "id": "imap_499065",
      "type": "general",
      "subj": "Formation offerte ISO 22361:2022 - Se Préparer à la gestion de crise",
      "from": "user",
      "date": "2026-03-05T09:00:06.000Z",
      "pseudo": {
        "source": "user",
        "username": "O.P."
      },
      "fps": {
        "mfr": [],
        "pid": []
      },
      "errs": [],
      "devices": [],
      "xref": [],
      "ghInfo": null,
      "forumInfo": null,
      "crashInfo": null,
      "ai": null,
      "homeyVersion": null,
      "appVersion": null,
      "bodyLength": 2022,
      "contentType": "text/plain"
    },
    {
      "id": "imap_499066",
      "type": "bug_report",
      "subj": "[Xpeng] Re: Type:Product",
      "from": "user",
      "date": "2026-03-05T09:06:32.000Z",
      "pseudo": {
        "source": "user",
        "username": "M.S."
      },
      "fps": {
        "mfr": [],
        "pid": []
      },
      "errs": [],
      "devices": [],
      "xref": [],
      "ghInfo": null,
      "forumInfo": null,
      "crashInfo": {
        "stackTraces": [],
        "crashApp": null,
        "capabilities": [],
        "clusters": []
      },
      "ai": null,
      "homeyVersion": null,
      "appVersion": null,
      "bodyLength": 2970,
      "contentType": "text/plain"
    },
    {
      "id": "imap_499070",
      "type": "crash_report",
      "subj": "Re: [JohanBendz/com.tuya.zigbee] Device Request - [Fingerbot Plus] - [_TZ3210_j4pdtz9v] / [TS0001] (Issue #869)",
      "from": "github",
      "date": "2026-03-05T09:11:43.000Z",
      "pseudo": {
        "source": "github",
        "username": "Kees Koertshuis"
      },
      "fps": {
        "mfr": [],
        "pid": []
      },
      "errs": [
        "Could not get device by id",
        "is not solved. also, when I run the code locally from VSC on docker I get the fo",
        "[err] [ManagerDrivers] [Driver:fingerbot] Error Initializing Device: Error: Cann",
        "find module '../../lib/tuya/TuyaZigbeeDevice'"
      ],
      "devices": [
        "for",
        "fingerbot",
        "Error"
      ],
      "xref": [],
      "ghInfo": null,
      "forumInfo": null,
      "crashInfo": {
        "stackTraces": [
          "Error Initializing Device: Error: Cannot find module '../../lib/tuya/TuyaZigbeeDevice'\r"
        ],
        "crashApp": null,
        "capabilities": [],
        "clusters": []
      },
      "ai": null,
      "homeyVersion": null,
      "appVersion": null,
      "bodyLength": 2333,
      "contentType": "text/plain"
    },
    {
      "id": "imap_499079",
      "type": "general",
      "subj": "[com.dlnraja.tuya.zigbee] Build #2025 has been created",
      "from": "homey_system",
      "date": "2026-03-05T09:52:41.000Z",
      "pseudo": {
        "source": "homey_system",
        "username": null
      },
      "fps": {
        "mfr": [],
        "pid": []
      },
      "errs": [],
      "devices": [],
      "xref": [],
      "ghInfo": null,
      "forumInfo": null,
      "crashInfo": null,
      "ai": null,
      "homeyVersion": null,
      "appVersion": null,
      "bodyLength": 508,
      "contentType": "text/html->text"
    },
    {
      "id": "imap_499080",
      "type": "general",
      "subj": "[com.dlnraja.tuya.zigbee] Your build is now draft",
      "from": "homey_system",
      "date": "2026-03-05T09:52:55.000Z",
      "pseudo": {
        "source": "homey_system",
        "username": null
      },
      "fps": {
        "mfr": [],
        "pid": []
      },
      "errs": [],
      "devices": [],
      "xref": [],
      "ghInfo": null,
      "forumInfo": null,
      "crashInfo": null,
      "ai": null,
      "homeyVersion": null,
      "appVersion": null,
      "bodyLength": 564,
      "contentType": "text/html->text"
    },
    {
      "id": "imap_499081",
      "type": "general",
      "subj": "[com.dlnraja.tuya.zigbee] Build #2025 is now testing",
      "from": "homey_system",
      "date": "2026-03-05T09:55:58.000Z",
      "pseudo": {
        "source": "homey_system",
        "username": null
      },
      "fps": {
        "mfr": [],
        "pid": []
      },
      "errs": [],
      "devices": [],
      "xref": [],
      "ghInfo": null,
      "forumInfo": null,
      "crashInfo": null,
      "ai": null,
      "homeyVersion": null,
      "appVersion": null,
      "bodyLength": 559,
      "contentType": "text/html->text"
    },
    {
      "id": "imap_499109",
      "type": "github",
      "subj": "Re: [JohanBendz/com.tuya.zigbee] Device Request - Wenz[greeting] Human Presence Sensor & Relay  - _TZE204_clrdrnya / WZ-235-ZB-RL TS0601 (Issue #1142)",
      "from": "github",
      "date": "2026-03-05T11:09:41.000Z",
      "pseudo": {
        "source": "github",
        "username": "dmz-86"
      },
      "fps": {
        "mfr": [
          "_TZE204_clrdrnya"
        ],
        "pid": [
          "TS0601"
        ]
      },
      "errs": [],
      "devices": [
        "mmWave"
      ],
      "xref": [
        {
          "fingerprint": "_TZE204_clrdrnya",
          "type": "mfr",
          "supported": true,
          "drivers": [
            "motion_sensor_radar_mmwave"
          ],
          "protocol": "tuya_dp",
          "requires": [
            "TuyaEF00Manager",
            "dpMappings"
          ]
        },
        {
          "fingerprint": "TS0601",
          "type": "pid",
          "supported": true,
          "drivers": [
            "air_purifier",
            "air_quality_co2",
            "air_quality_comprehensive",
            "button_emergency_sos",
            "button_wireless_6",
            "ceiling_fan",
            "climate_sensor",
            "co_sensor",
            "contact_sensor",
            "curtain_motor",
            "curtain_motor_tilt",
            "dimmer_3gang",
            "dimmer_dual_channel",
            "dimmer_wall_1gang",
            "din_rail_meter",
            "din_rail_switch",
            "door_controller",
            "doorbell",
            "energy_meter_3phase",
            "fan_controller",
            "fingerprint_lock",
            "floor_heating_thermostat",
            "formaldehyde_sensor",
            "garage_door",
            "garage_door_opener",
            "gas_detector",
            "gas_sensor",
            "generic_tuya",
            "humidifier",
            "hvac_air_conditioner",
            "hvac_controller",
            "hvac_dehumidifier",
            "ir_blaster",
            "lcdtemphumidsensor",
            "light_sensor_outdoor",
            "lock_smart",
            "motion_sensor",
            "motion_sensor_radar_mmwave",
            "pet_feeder",
            "pet_feeder_zigbee",
            "plug_energy_monitor",
            "plug_smart",
            "pool_pump",
            "power_clamp_meter",
            "power_meter",
            "presence_sensor_ceiling",
            "presence_sensor_radar",
            "radiator_controller",
            "radiator_valve",
            "radiator_valve_zigbee",
            "rain_sensor",
            "scene_switch_4",
            "shutter_roller_controller",
            "siren",
            "smart_breaker",
            "smart_heater",
            "smart_heater_controller",
            "smart_lcd_thermostat",
            "smart_rcbo",
            "smart_scene_panel",
            "smoke_detector_advanced",
            "soil_sensor",
            "switch_1gang",
            "switch_2gang",
            "switch_3gang",
            "switch_4gang",
            "switch_dimmer_1gang",
            "switch_wall_5gang",
            "switch_wall_6gang",
            "switch_wall_8gang",
            "thermostat_4ch",
            "thermostat_tuya_dp",
            "universal_fallback",
            "usb_outlet_advanced",
            "valve_irrigation",
            "valve_single",
            "vibration_sensor",
            "water_leak_sensor",
            "water_tank_monitor",
            "water_valve_smart",
            "weather_station_outdoor"
          ],
          "multiDriver": true
        }
      ],
      "ghInfo": {
        "issueNum": "1142",
        "action": null,
        "fps": {
          "mfr": [
            "_TZE204_clrdrnya"
          ],
          "pid": [
            "TS0601"
          ]
        },
        "isNew": false,
        "repo": "JohanBendz/com.tuya.zigbee",
        "labels": null,
        "author": "dmz-86",
        "bodyExcerpt": "dmz-86 left a comment (JohanBendz/com.tuya.zigbee#1142)\r\n\r\nNothing changed.\r\n\r\nDevice: mmWave Human Presence Radar\r\nmodelId: TS0601\r\nmanufacturerName: _TZE204_clrdrnya\r\npowerSource: mains (not battery-powered)\r\n\r\nCurrent wrong capabilities being mapped:\r\n- measure_battery (should not exist, device is mains powered)\r\n- measure_temperature (wrong DP mapping)  \r\n- measure_humidity (wrong DP mapping)\r\n\r\nExpected capabilities:\r\n- alarm_motion (human presence detection)\r\n\r\nThe device is being matched "
      },
      "forumInfo": null,
      "crashInfo": null,
      "ai": null,
      "homeyVersion": null,
      "appVersion": null,
      "bodyLength": 869,
      "contentType": "text/plain"
    },
    {
      "id": "imap_499118",
      "type": "github",
      "subj": "Re: [dlnraja/com.tuya.zigbee] [DEVICE] Presence Sensor Radar:   zb_product_id    \"TS0225\" - zb_manufacturer_name     \"_TZ321C_fkzihaxe8\" - Wenz[greeting] get any value. (Issue #97)",
      "from": "github",
      "date": "2026-03-05T12:11:25.000Z",
      "pseudo": {
        "source": "github",
        "username": "NoroddH"
      },
      "fps": {
        "mfr": [],
        "pid": []
      },
      "errs": [],
      "devices": [],
      "xref": [],
      "ghInfo": {
        "issueNum": "97",
        "action": null,
        "fps": {
          "mfr": [],
          "pid": []
        },
        "isNew": false,
        "repo": "dlnraja/com.tuya.zigbee",
        "labels": null,
        "author": "NoroddH",
        "bodyExcerpt": "NoroddH left a comment (dlnraja/com.tuya.zigbee#97)\r\n\r\nI have bought a tuya gateway and when i connect the presence_sensor to the gateway i got following masurements\r\nLuminance: in Lux\r\nDistance: in meter\r\nand Human present. Added a picture from gateway. \r\n\r\n![Image](https://github.com/user-attachments/assets/430e[REDACTED_PHONE]dc3-9426-c900ed3a08a7)\r\n\r\nWhen I connect it to Homey the measurements as seen in developer tools is not correct.  Add picture:\r\n\r\n<img width=\"712\" height=\"454\" alt=\"Imag"
      },
      "forumInfo": null,
      "crashInfo": null,
      "ai": null,
      "homeyVersion": null,
      "appVersion": null,
      "bodyLength": 1005,
      "contentType": "text/plain"
    },
    {
      "id": "imap_499119",
      "type": "github",
      "subj": "Re: [dlnraja/com.tuya.zigbee] [DEVICE] Presence Sensor Radar:   zb_product_id    \"TS0225\" - zb_manufacturer_name     \"_TZ321C_fkzihaxe8\" - Wenz[greeting] get any value. (Issue #97)",
      "from": "github",
      "date": "2026-03-05T12:11:34.000Z",
      "pseudo": {
        "source": "github",
        "username": "github-actions[bot]"
      },
      "fps": {
        "mfr": [],
        "pid": []
      },
      "errs": [],
      "devices": [],
      "xref": [],
      "ghInfo": {
        "issueNum": "97",
        "action": "opened",
        "fps": {
          "mfr": [],
          "pid": []
        },
        "isNew": true,
        "repo": "dlnraja/com.tuya.zigbee",
        "labels": null,
        "author": "github-actions[bot]",
        "bodyExcerpt": "Reopened #97.\r\n\r\n-- \r\nReply to this email directly or view it on GitHub:\r\nhttps://github.com/dlnraja/com.tuya.zigbee/issues/97#event[REDACTED_PHONE]\r\nYou are receiving this because you modified the open/close state.\r\n\r\nMessage ID: <dlnraja/com.tuya.zigbee/issue/97/issue_event/[REDACTED_EMAIL]>\r\n"
      },
      "forumInfo": null,
      "crashInfo": null,
      "ai": null,
      "homeyVersion": null,
      "appVersion": null,
      "bodyLength": 296,
      "contentType": "text/plain"
    },
    {
      "id": "imap_499120",
      "type": "github",
      "subj": "Re: [dlnraja/com.tuya.zigbee] [DEVICE] Presence Sensor Radar:   zb_product_id    \"TS0225\" - zb_manufacturer_name     \"_TZ321C_fkzihaxe8\" - Wenz[greeting] get any value. (Issue #97)",
      "from": "github",
      "date": "2026-03-05T12:11:37.000Z",
      "pseudo": {
        "source": "github",
        "username": "github-actions[bot]"
      },
      "fps": {
        "mfr": [],
        "pid": []
      },
      "errs": [],
      "devices": [
        "Interview",
        "settings"
      ],
      "xref": [],
      "ghInfo": {
        "issueNum": "97",
        "action": "opened",
        "fps": {
          "mfr": [],
          "pid": []
        },
        "isNew": true,
        "repo": "dlnraja/com.tuya.zigbee",
        "labels": null,
        "author": "github-actions[bot]",
        "bodyExcerpt": "github-actions[bot] left a comment (dlnraja/com.tuya.zigbee#97)\r\n\r\n<!-- tuya-reopen-bot -->\r\nThis issue has been **automatically reopened** because @NoroddH posted a new comment.\r\nIt will be reviewed in the next automation cycle.\r\n\r\n> If your device is still not working, please share:\r\n> 1. **Device Interview** from [Developer Tools](https://tools.developer.homey.app)\r\n> 2. **Diagnostic Report ID** from device settings\r\n\r\n-- \r\nReply to this email directly or view it on GitHub:\r\nhttps://github.co"
      },
      "forumInfo": null,
      "crashInfo": null,
      "ai": null,
      "homeyVersion": null,
      "appVersion": null,
      "bodyLength": 701,
      "contentType": "text/plain"
    },
    {
      "id": "imap_499121",
      "type": "github",
      "subj": "Re: [dlnraja/com.tuya.zigbee] [DEVICE] Presence Sensor Radar:   zb_product_id    \"TS0225\" - zb_manufacturer_name     \"_TZ321C_fkzihaxe8\" - Wenz[greeting] get any value. (Issue #97)",
      "from": "github",
      "date": "2026-03-05T12:13:17.000Z",
      "pseudo": {
        "source": "github",
        "username": "NoroddH"
      },
      "fps": {
        "mfr": [
          "_TZ321C_fkzihax8"
        ],
        "pid": [
          "TS0225"
        ]
      },
      "errs": [],
      "devices": [],
      "xref": [
        {
          "fingerprint": "_TZ321C_fkzihax8",
          "type": "mfr",
          "supported": true,
          "drivers": [
            "presence_sensor_radar"
          ],
          "protocol": "unknown",
          "requires": []
        },
        {
          "fingerprint": "TS0225",
          "type": "pid",
          "supported": true,
          "drivers": [
            "gas_sensor",
            "motion_sensor",
            "presence_sensor_radar",
            "universal_fallback"
          ],
          "multiDriver": true
        }
      ],
      "ghInfo": {
        "issueNum": "97",
        "action": null,
        "fps": {
          "mfr": [
            "_TZ321C_fkzihax8"
          ],
          "pid": [
            "TS0225"
          ]
        },
        "isNew": false,
        "repo": "dlnraja/com.tuya.zigbee",
        "labels": null,
        "author": "NoroddH",
        "bodyExcerpt": "NoroddH left a comment (dlnraja/com.tuya.zigbee#97)\r\n\r\n\r\n  \"ids\": {\r\n    \"modelId\": \"TS0225\",\r\n    \"manufacturerName\": \"_TZ321C_fkzihax8\"\r\n  },\r\n  \"endpoints\": {\r\n    \"endpointDescriptors\": [\r\n      {\r\n        \"endpointId\": 1,\r\n        \"applicationProfileId\": 260,\r\n        \"applicationDeviceId\": 1026,\r\n        \"applicationDeviceVersion\": 0,\r\n        \"_reserved1\": 1,\r\n        \"inputClusters\": [\r\n          0,\r\n          4,\r\n          5,\r\n          1280\r\n        ],\r\n        \"outputClusters\": [\r\n   "
      },
      "forumInfo": null,
      "crashInfo": null,
      "ai": null,
      "homeyVersion": null,
      "appVersion": null,
      "bodyLength": 13414,
      "contentType": "text/plain"
    },
    {
      "id": "imap_499124",
      "type": "github",
      "subj": "Re: [dlnraja/com.tuya.zigbee] [DEVICE] Presence Sensor Radar:   zb_product_id    \"TS0225\" - zb_manufacturer_name     \"_TZ321C_fkzihaxe8\" - Wenz[greeting] get any value. (Issue #97)",
      "from": "github",
      "date": "2026-03-05T12:21:52.000Z",
      "pseudo": {
        "source": "github",
        "username": "NoroddH"
      },
      "fps": {
        "mfr": [],
        "pid": []
      },
      "errs": [],
      "devices": [],
      "xref": [],
      "ghInfo": {
        "issueNum": "97",
        "action": null,
        "fps": {
          "mfr": [],
          "pid": []
        },
        "isNew": false,
        "repo": "dlnraja/com.tuya.zigbee",
        "labels": null,
        "author": "NoroddH",
        "bodyExcerpt": "NoroddH left a comment (dlnraja/com.tuya.zigbee#97)\r\n\r\nAfter I runned the interview and saved the Advanced settings data then I got this Motion Sensor data from developer tool.\r\n\r\n<img width=\"804\" height=\"875\" alt=\"Image\" src=\"https://github.com/user-attachments/assets/77f115aa-9bd1-4b47-bc29-82ef7ed27a1f\" />\r\n\r\n<img width=\"1140\" height=\"815\" alt=\"Image\" src=\"https://github.com/user-attachments/assets/d2c495cc-ce55-439f-b8a7-b300de8e7787\" />\r\n\r\n-- \r\nReply to this email directly or view it on Git"
      },
      "forumInfo": null,
      "crashInfo": null,
      "ai": null,
      "homeyVersion": null,
      "appVersion": null,
      "bodyLength": 724,
      "contentType": "text/plain"
    },
    {
      "id": "imap_503854",
      "type": "diagnostic",
      "subj": "[com.dlnraja.tuya.zigbee] Your app has received a Diagnostics Report",
      "from": "homey_system",
      "date": "2026-04-03T06:12:58.000Z",
      "pseudo": {
        "source": "homey_system",
        "username": null
      },
      "fps": {
        "mfr": [],
        "pid": []
      },
      "errs": [],
      "devices": [
        "switch_dimmer_1gang",
        "switch_wireless",
        "temphumidsensor",
        "initialized",
        "switch_plug_1",
        "thermostat_4ch",
        "thermostat_tuya_dp",
        "switch_plug_2",
        "universal_fallback",
        "switch_temp_sensor",
        "usb_dongle_dual_repeater",
        "usb_dongle_triple",
        "usb_outlet_advanced",
        "valve_irrigation",
        "valve_single",
        "vibration_sensor",
        "wall_remote_2_gang",
        "init",
        "wall_curtain_switch",
        "wall_remote_1_gang",
        "wall_dimmer_1gang_1way",
        "has",
        "wall_remote_3_gang",
        "wall_remote_4_gang",
        "wall_remote_4_gang_2",
        "wall_remote_4_gang_3",
        "wall_remote_6_gang",
        "wall_switch_1gang_1way",
        "wall_switch_2gang_1way",
        "wall_switch_3gang_1way",
        "wall_switch_4gang_1way",
        "water_leak_sensor",
        "water_tank_monitor",
        "initializing",
        "water_valve_garden",
        "water_valve_smart",
        "weather_station_outdoor",
        "wifi_air_purifier",
        "wifi_camera",
        "wifi_air_quality",
        "wifi_cover",
        "wifi_dehumidifier",
        "wifi_dimmer",
        "wifi_door_lock",
        "wifi_doorbell",
        "wifi_ewelink_bulb",
        "wifi_ewelink_dimmer",
        "wifi_ewelink_fan",
        "wifi_ewelink_led",
        "wifi_ewelink_plug",
        "wifi_ewelink_pow",
        "wifi_ewelink_switch",
        "wifi_ewelink_switch_2ch",
        "wifi_ewelink_switch_4ch",
        "wifi_ewelink_th",
        "wifi_garage_door",
        "wifi_generic",
        "wifi_heater",
        "wifi_ir_remote",
        "wifi_humidifier"
      ],
      "xref": [],
      "ghInfo": null,
      "forumInfo": null,
      "crashInfo": null,
      "ai": null,
      "homeyVersion": null,
      "appVersion": null,
      "bodyLength": 16792,
      "contentType": "text/html->text"
    },
    {
      "id": "imap_503856",
      "type": "github",
      "subj": "Re: [dlnraja/com.tuya.zigbee] Device Request - Temperature &humidity sensor with external probe - Shenzen New Green Energy Techologies Co ltd / _TZE284_8se38w3c TS0601 (Issue #184)",
      "from": "github",
      "date": "2026-04-03T06:14:20.000Z",
      "pseudo": {
        "source": "github",
        "username": "pemikalsen-sudo"
      },
      "fps": {
        "mfr": [],
        "pid": []
      },
      "errs": [],
      "devices": [],
      "xref": [],
      "ghInfo": {
        "issueNum": "184",
        "action": "commented",
        "fps": {
          "mfr": [],
          "pid": []
        },
        "isNew": false,
        "repo": "dlnraja/com.tuya.zigbee",
        "labels": null,
        "author": "pemikalsen-sudo",
        "bodyExcerpt": "pemikalsen-sudo left a comment (dlnraja/com.tuya.zigbee#184)\r\n\r\nHello.\r\nI have made an app diagnostic report for your app. I got this reference number: 7849d214-b61d-4a40-9f73-9362d7895f38\r\n\r\n-- \r\nReply to this email directly or view it on GitHub:\r\nhttps://github.com/dlnraja/com.tuya.zigbee/issues/184#issuecomment[REDACTED_PHONE]\r\nYou are receiving this because you commented.\r\n\r\nMessage ID: <dlnraja/com.tuya.zigbee/issues/184/[REDACTED_EMAIL]>\r\n"
      },
      "forumInfo": null,
      "crashInfo": null,
      "ai": null,
      "homeyVersion": null,
      "appVersion": null,
      "bodyLength": 449,
      "contentType": "text/plain"
    }
  ]
}