{
  "id": "cover-ikea-ikea-shade-756",
  "name": {
    "en": "ikea shade",
    "fr": "ikea shade",
    "nl": "ikea shade",
    "ta": "ikea shade"
  },
  "capabilities": [
    "windowcoverings_set",
    "windowcoverings_state"
  ],
  "zigbee": {
    "manufacturerName": [
      "ikea",
      "IKEA"
    ],
    "modelId": [
      "ikea-shade-756",
      "ikea-chime-70",
      "ikea-chime-608",
      "ikea-buzzer-255",
      "ikea-buzzer-232",
      "ikea-alarm-707",
      "ikea-alarm-641",
      "ikea-water-667",
      "ikea-water-362",
      "ikea-thermostat-39",
      "ikea-thermostat-128",
      "ikea-temperature-892",
      "ikea-temperature-466",
      "ikea-switch-783",
      "ikea-switch-612",
      "ikea-smoke-94",
      "ikea-smoke-360",
      "ikea-smart-647",
      "ikea-smart-315",
      "ikea-power-769",
      "ikea-power-457",
      "ikea-outlet-136",
      "ikea-outlet-132",
      "ikea-motion-981",
      "ikea-motion-927",
      "ikea-humidity-712",
      "ikea-humidity-288",
      "ikea-heater-896",
      "ikea-heater-399",
      "ikea-gas-418",
      "ikea-gas-317",
      "ikea-fan-208",
      "ikea-fan-18",
      "ikea-contact-739",
      "ikea-contact-348",
      "ikea-ac-728",
      "ikea-ac-165",
      "ikea-padlock-984",
      "ikea-padlock-134",
      "ikea-door-555",
      "ikea-door-491",
      "ikea-deadbolt-42",
      "ikea-deadbolt-274",
      "ikea-wall-993",
      "ikea-wall-697",
      "ikea-table-357",
      "ikea-table-218",
      "ikea-strip-96",
      "ikea-strip-461",
      "ikea-garden-901",
      "ikea-garden-130",
      "ikea-floor-708",
      "ikea-floor-238",
      "ikea-ceiling-940",
      "ikea-ceiling-558",
      "ikea-bulb-793",
      "ikea-bulb-320",
      "ts130f",
      "ts0601",
      "ts011f",
      "ts0121",
      "tso121",
      "rh3052",
      "ts0201",
      "rh3001",
      "ts0203",
      "ts0207",
      "ts0014",
      "ts0044",
      "ts0003",
      "ts0013",
      "ts0043",
      "ts0002",
      "ts0012",
      "ts0042",
      "ts0001",
      "ts0011",
      "ts0046",
      "ts004f",
      "ts0041",
      "ts0111",
      "ts0502a",
      "ts0004",
      "ts000f",
      "ts0115",
      "ts0205",
      "ts0215a",
      "ty0202",
      "ts0101",
      "ts0049",
      "ty0203",
      "ts0202",
      "ts0505a",
      "ts0505b",
      "ts0503a",
      "ts0503b",
      "ts0504b",
      "ts0225",
      "ty0201",
      "ts0222",
      "mct-340 e",
      "ts110f",
      "ts110e",
      "ts0052",
      "ts0502b",
      "rh3040",
      "doorwindow-sensor-zb3.0",
      "ikea-shade-837",
      "ikea-garage-65",
      "ikea-garage-4",
      "ikea-curtain-431",
      "ikea-curtain-339",
      "ikea-blind-515",
      "ikea-blind-14"
    ]
  }
}