{
  "id": "osram-motion-12",
  "name": {
    "en": "osram-motion-12 Device",
    "fr": "Appareil osram-motion-12",
    "nl": "osram-motion-12 Apparaat",
    "ta": "osram-motion-12 சாதனம்"
  },
  "class": "sensor",
  "capabilities": [
    "alarm_motion"
  ],
  "zigbee": {
    "manufacturerName": "Generic",
    "modelId": "OSRAM-MOTION-12",
    "clusters": [
      "genBasic",
      "genIdentify",
      "msOccupancySensing"
    ]
  },
  "settings": [],
  "images": {
    "small": "osram-motion-12.png",
    "large": "osram-motion-12.png"
  }
}