[
  {
    "id": "motion_alarm_true",
    "title": {
      "en": "Motion detected",
      "fr": "Mouvement détecté",
      "nl": "Beweging gedetecteerd",
      "de": "Bewegung erkannt"
    },
    "titleFormatted": {
      "en": "Motion was detected by [[device]]",
      "fr": "Mouvement détecté par [[device]]",
      "nl": "Beweging gedetecteerd door [[device]]",
      "de": "Bewegung erkannt von [[device]]"
    },
    "args": [
      {
        "name": "device",
        "type": "device",
        "filter": "driver_id=tuya_motion_sensor"
      }
    ]
  },
  {
    "id": "device_temperature_changed",
    "title": {
      "en": "Temperature changed",
      "fr": "Température changée",
      "nl": "Temperatuur veranderd",
      "de": "Temperatur geändert"
    },
    "titleFormatted": {
      "en": "Temperature of [[device]] changed",
      "fr": "Température de [[device]] a changé",
      "nl": "Temperatuur van [[device]] is veranderd",
      "de": "Temperatur von [[device]] hat sich geändert"
    },
    "args": [
      {
        "name": "device",
        "type": "device",
        "filter": "capability_id=measure_temperature"
      }
    ],
    "tokens": [
      {
        "name": "temperature",
        "type": "number",
        "title": {
          "en": "Temperature (°C)",
          "fr": "Température (°C)",
          "nl": "Temperatuur (°C)",
          "de": "Temperatur (°C)"
        }
      }
    ]
  },
  {
    "id": "device_turned_on",
    "title": {
      "en": "Device turned on",
      "fr": "Appareil allumé",
      "nl": "Apparaat ingeschakeld",
      "de": "Gerät eingeschaltet"
    },
    "titleFormatted": {
      "en": "[[device]] was turned on",
      "fr": "[[device]] a été allumé",
      "nl": "[[device]] werd ingeschakeld",
      "de": "[[device]] wurde eingeschaltet"
    },
    "args": [
      {
        "name": "device",
        "type": "device",
        "filter": "capability_id=onoff"
      }
    ]
  },
  {
    "id": "device_battery_low",
    "title": {
      "en": "Battery low",
      "fr": "Batterie faible",
      "nl": "Batterij laag",
      "de": "Batterie schwach"
    },
    "titleFormatted": {
      "en": "Battery of [[device]] is low",
      "fr": "Batterie de [[device]] est faible",
      "nl": "Batterij van [[device]] is laag",
      "de": "Batterie von [[device]] ist schwach"
    },
    "args": [
      {
        "name": "device",
        "type": "device",
        "filter": "capability_id=measure_battery"
      }
    ],
    "tokens": [
      {
        "name": "battery",
        "type": "number",
        "title": {
          "en": "Battery level (%)",
          "fr": "Niveau batterie (%)",
          "nl": "Batterijniveau (%)",
          "de": "Batteriestand (%)"
        }
      }
    ]
  },
  {
    "id": "water_leak_detected",
    "title": {
      "en": "Water leak detected",
      "fr": "Fuite d'eau détectée",
      "nl": "Waterlek gedetecteerd",
      "de": "Wasserleck erkannt"
    },
    "titleFormatted": {
      "en": "Water leak detected by [[device]]",
      "fr": "Fuite d'eau détectée par [[device]]",
      "nl": "Waterlek gedetecteerd door [[device]]",
      "de": "Wasserleck erkannt von [[device]]"
    },
    "args": [
      {
        "name": "device",
        "type": "device",
        "filter": "driver_id=tuya_water_leak_sensor"
      }
    ]
  },
  {
    "id": "smoke_detected",
    "title": {
      "en": "Smoke detected",
      "fr": "Fumée détectée",
      "nl": "Rook gedetecteerd", 
      "de": "Rauch erkannt"
    },
    "titleFormatted": {
      "en": "Smoke detected by [[device]]",
      "fr": "Fumée détectée par [[device]]",
      "nl": "Rook gedetecteerd door [[device]]",
      "de": "Rauch erkannt von [[device]]"
    },
    "args": [
      {
        "name": "device",
        "type": "device",
        "filter": "driver_id=tuya_smoke_sensor"
      }
    ]
  },
  {
    "id": "contact_alarm_changed",
    "title": {
      "en": "Door/Window opened or closed",
      "fr": "Porte/Fenêtre ouverte ou fermée",
      "nl": "Deur/Raam geopend of gesloten",
      "de": "Tür/Fenster geöffnet oder geschlossen"
    },
    "titleFormatted": {
      "en": "[[device]] was [[state]]",
      "fr": "[[device]] a été [[state]]",
      "nl": "[[device]] werd [[state]]", 
      "de": "[[device]] wurde [[state]]"
    },
    "args": [
      {
        "name": "device",
        "type": "device",
        "filter": "driver_id=tuya_door_window_sensor"
      }
    ],
    "tokens": [
      {
        "name": "state",
        "type": "string",
        "title": {
          "en": "State",
          "fr": "État",
          "nl": "Status",
          "de": "Zustand"
        }
      }
    ]
  }
]
